{
  "_fv": 79,
  "_type": "recipe",
  "definition": {
    "recipeType": "Crafting",
    "recipeRetstackSize": 1,
    "group": "",
    "unlockingItems": [],
    "cookingBookCategory": "MISC",
    "xpReward": 0.0,
    "cookingTime": 200,
    "craftingBookCategory": "MISC",
    "recipeShapeless": false,
    "recipeSlots": [
      {
        "value": "CUSTOM:IronMachineBolt"
      },
      {
        "value": "CUSTOM:IronMachineBolt"
      },
      {
        "value": "CUSTOM:IronMachineBolt"
      },
      {
        "value": "CUSTOM:LaserDiode"
      },
      {
        "value": "CUSTOM:ComputationNode"
      },
      {
        "value": "CUSTOM:Silicon"
      },
      {
        "value": ""
      },
      {
        "value": ""
      },
      {
        "value": "Items.IRON_INGOT"
      }
    ],
    "recipeReturnStack": {
      "value": "CUSTOM:OreScanner"
    },
    "name": "ore_scanner_recipe",
    "namespace": "mod"
  }
}